{"law_id":"428M60020000003","title":"個人情報の保護に関する法律施行規則","group":"個人情報","type":"規則","from_revision":"428M60020000003_20260401_508M60020000001","to_revision":"428M60020000003_20260614_508M60020000002","to_updated":"2026-06-24T09:19:41+09:00","generatedAt":"2026-06-24T23:46:42.601Z","articles":[{"status":"changed","num":"第4条","cap":"（旅券の番号等に準ずる文字、番号、記号その他の符号）","oldCap":"（旅券の番号等に準ずる文字、番号、記号その他の符号）","old":"令第1条第10号の個人情報保護委員会規則で定める文字、番号、記号その他の符号は、次に掲げるものとする。\n　1 健康保険法（大正11年法律第70号）第3条第11項に規定する保険者番号及び同条第12項に規定する被保険者等記号・番号\n　2 船員保険法（昭和14年法律第73号）第2条第10項に規定する保険者番号及び同条第11項に規定する被保険者等記号・番号\n　3 出入国管理及び難民認定法（昭和26年政令第319号）第2条第5号に規定する旅券（日本国政府の発行したものを除く。）の番号\n　4 出入国管理及び難民認定法第19条の4第1項第5号の在留カードの番号\n　5 私立学校教職員共済法（昭和28年法律第245号）第45条第1項に規定する加入者等記号・番号等\n　6 国家公務員共済組合法（昭和33年法律第128号）第112条の2第1項に規定する組合員等記号・番号等\n　7 地方公務員等共済組合法（昭和37年法律第152号）第144条の24の2第1項に規定する組合員等記号・番号等\n　8 雇用保険法施行規則（昭和50年労働省令第3号）第10条第1項の雇用保険被保険者証の被保険者番号\n　9 日本国との平和条約に基づき日本の国籍を離脱した者等の出入国管理に関する特例法（平成3年法律第71号）第8条第1項第3号の特別永住者証明書の番号","new":"令第1条第10号の個人情報保護委員会規則で定める文字、番号、記号その他の符号は、次に掲げるものとする。\n　1 健康保険法（大正11年法律第70号）第3条第11項に規定する保険者番号及び同条第12項に規定する被保険者等記号・番号\n　2 船員保険法（昭和14年法律第73号）第2条第10項に規定する保険者番号及び同条第11項に規定する被保険者等記号・番号\n　3 出入国管理及び難民認定法（昭和26年政令第319号）第2条第5号に規定する旅券（日本国政府の発行したものを除く。）の番号\n　4 出入国管理及び難民認定法第19条の4第1項第4号の在留カードの番号\n　5 私立学校教職員共済法（昭和28年法律第245号）第45条第1項に規定する加入者等記号・番号等\n　6 国家公務員共済組合法（昭和33年法律第128号）第112条の2第1項に規定する組合員等記号・番号等\n　7 地方公務員等共済組合法（昭和37年法律第152号）第144条の24の2第1項に規定する組合員等記号・番号等\n　8 雇用保険法施行規則（昭和50年労働省令第3号）第10条第1項の雇用保険被保険者証の被保険者番号\n　9 日本国との平和条約に基づき日本の国籍を離脱した者等の出入国管理に関する特例法（平成3年法律第71号）第8条第1項第3号の特別永住者証明書の番号"}]}